scr/__init__.py
scr/datacleaning.py
datasanitize-0.0.1.dist-info/LICENSE
datasanitize-0.0.1.dist-info/METADATA
datasanitize-0.0.1.dist-info/WHEEL
datasanitize-0.0.1.dist-info/top_level.txt
datasanitize-0.0.1.dist-info/RECORD
