Metadata-Version: 2.1
Name: datasanitize
Version: 0.0.1
Summary: A data cleaning package and visualisation tool for data science projects
Home-page: https://github.com/muganga-charles/dstrial
Author: Charles Muganga
Author-email: Charles Muganga <mugangacharles5@gmail.com>
License: MIT
Project-URL: Homepage, https://github.com/muganga-charles
Classifier: Programming Language :: Python :: 3
Classifier: License :: OSI Approved :: MIT License
Classifier: Operating System :: OS Independent
Requires-Python: >=3.7
License-File: LICENSE
Requires-Dist: pandas
Requires-Dist: numpy
Requires-Dist: matplotlib
Requires-Dist: seaborn
Requires-Dist: scipy
Requires-Dist: sklearn
